babyrobot/__init__.py
babyrobot/_version.py
babyrobot/envs/__init__.py
babyrobot/envs/baby_robot_env_v0.py
babyrobot/envs/baby_robot_env_v1.py
babyrobot/envs/baby_robot_env_v2.py
babyrobot/envs/baby_robot_env_v3.py
babyrobot/envs/baby_robot_env_v4.py
babyrobot/envs/baby_robot_env_v5.py
babyrobot/envs/baby_robot_env_v6.py
babyrobot/envs/baby_robot_env_v7.py
babyrobot/envs/baby_robot_interface.py
babyrobot/envs/baby_robot_v0.py
babyrobot/envs/lib/__init__.py
babyrobot/envs/lib/actions.py
babyrobot/envs/lib/arrows.py
babyrobot/envs/lib/direction.py
babyrobot/envs/lib/draw_grid.py
babyrobot/envs/lib/draw_grid_test.py
babyrobot/envs/lib/draw_info.py
babyrobot/envs/lib/dynamic_space.py
babyrobot/envs/lib/graphical_grid_level.py
babyrobot/envs/lib/grid_base.py
babyrobot/envs/lib/grid_info.py
babyrobot/envs/lib/grid_level.py
babyrobot/envs/lib/maze.py
babyrobot/envs/lib/robot.py
babyrobot/envs/lib/robot_draw.py
babyrobot/envs/lib/robot_draw_test.py
babyrobot/envs/lib/robot_position.py
babyrobot/envs/lib/images/BabyRobot64_Sprites.png
babyrobot/envs/lib/images/baby_robot_0.png
babyrobot/envs/lib/images/baby_robot_1.png
babyrobot/envs/lib/images/baby_robot_10.png
babyrobot/envs/lib/images/baby_robot_2.png
babyrobot/envs/lib/images/baby_robot_3.png
babyrobot/envs/lib/images/baby_robot_4.png
babyrobot/envs/lib/images/baby_robot_5.png
babyrobot/envs/lib/images/baby_robot_6.png
babyrobot/envs/lib/images/baby_robot_7.png
babyrobot/envs/lib/images/baby_robot_8.png
babyrobot/envs/lib/images/baby_robot_9.png
babyrobot/envs/lib/images/big_puddle.png
babyrobot/envs/lib/images/small_puddle.png
babyrobot/envs/lib/images/splash_2.png
babyrobot/envs/lib/themes/black_orange.json
babyrobot/envs/lib/themes/blue_green.json
babyrobot/envs/lib/themes/green.json
babyrobot/lib/__init__.py
babyrobot/lib/animation.py
babyrobot/lib/deterministic_policy.py
babyrobot/lib/monte_carlo copy.py
babyrobot/lib/monte_carlo.py
babyrobot/lib/policy.py
babyrobot/lib/policy_evaluation.py
babyrobot/lib/utils.py
babyrobot-1.0.40.dist-info/LICENSE
babyrobot-1.0.40.dist-info/METADATA
babyrobot-1.0.40.dist-info/WHEEL
babyrobot-1.0.40.dist-info/top_level.txt
babyrobot-1.0.40.dist-info/RECORD
