Metadata-Version: 2.1
Name: babyrobot
Version: 1.0.40
Summary: An OpenAI Gym Environment for BabyRobot
Home-page: https://github.com/WhatIThinkAbout/BabyRobotGym
Author: Steve Roberts
Author-email: steve@steveroberts.name
License: MIT
Classifier: License :: OSI Approved :: MIT License
Classifier: Programming Language :: Python
Classifier: Programming Language :: Python :: 3
License-File: LICENSE
Requires-Dist: gymnasium (==0.27.0)
Requires-Dist: ipycanvas (==0.11)
Requires-Dist: imageio (==2.23.0)
Requires-Dist: tqdm (==4.64.0)
